Day 6/Question 2/parity_checker.v
module parity_checker (
    input  [3:0] D,
    input P,     
    input mode,
    output reg error
);
    always @(*) begin
        if (mode == 1'b0)
            error = ^{D, P};   
        else
            error = ~^{D, P};   
    end
endmodule


/*output
meenakshi@meenakshi-Inspiron-3501:~/verilog/parity_checker$ vvp parity_checker.out
VCD info: dumpfile parity_checker.vcd opened for output.
$time=0|D=1011|P=1|mode=0|error=0
$time=10|D=1100|P=0|mode=0|error=0
$time=20|D=1011|P=0|mode=0|error=1
$time=30|D=1100|P=1|mode=0|error=1
$time=40|D=1011|P=0|mode=1|error=0
$time=50|D=1100|P=1|mode=1|error=0
$time=60|D=1011|P=1|mode=1|error=1
$time=70|D=1100|P=0|mode=1|error=1
parity_checker_tb.v:31: $finish called at 80 (1s)
*/

Day 6/Question 2/parity_checker_tb.v
module parity_checker_tb;
    reg  [3:0] D;
    reg        P;
    reg        mode;
    wire       error;
//instantiate
    parity_checker dut (
        .D(D),
        .P(P),
        .mode(mode),
        .error(error)
    );
    initial begin
        $monitor("$time=%0t|D=%b|P=%b|mode=%b|error=%b",$time,D,P,mode,error);
        $dumpfile("parity_checker.vcd");
        $dumpvars(0, parity_checker_tb);
        mode = 0;
        D = 4'b1011; P = 1'b1; #10;   
        D = 4'b1100; P = 1'b0; #10;   

        D = 4'b1011; P = 1'b0; #10;
        D = 4'b1100; P = 1'b1; #10;

        mode = 1;
        D = 4'b1011; P = 1'b0; #10;   
        D = 4'b1100; P = 1'b1; #10;   

        D = 4'b1011; P = 1'b1; #10;
        D = 4'b1100; P = 1'b0; #10;

        $finish;
    end
endmodule

Day 6/Question 2/parity_checker.vcd
$date
	Wed Dec 17 12:10:52 2025
$end
$version
	Icarus Verilog
$end
$timescale
	1s
$end
$scope module parity_checker_tb $end
$var wire 1 ! error $end
$var reg 4 " D [3:0] $end
$var reg 1 # P $end
$var reg 1 $ mode $end
$scope module dut $end
$var wire 4 % D [3:0] $end
$var wire 1 # P $end
$var wire 1 $ mode $end
$var reg 1 ! error $end
$upscope $end
$upscope $end
$enddefinitions $end
$comment Show the parameter values. $end
$dumpall
$end
#0
$dumpvars
b1011 %
0$
1#
b1011 "
0!
$end
#10
0#
b1100 "
b1100 %
#20
1!
b1011 "
b1011 %
#30
1#
b1100 "
b1100 %
#40
0!
0#
b1011 "
b1011 %
1$
#50
1#
b1100 "
b1100 %
#60
1!
b1011 "
b1011 %
#70
0#
b1100 "
b1100 %
