Day 5/Question 6/demux1to8.v
module demux1to8 (
    input  D,
    input  [2:0] S,
    output Y0, Y1, Y2, Y3,
    output Y4, Y5, Y6, Y7
);
    assign Y0 = D & ~S[2] & ~S[1] & ~S[0];
    assign Y1 = D & ~S[2] & ~S[1] &  S[0];
    assign Y2 = D & ~S[2] &  S[1] & ~S[0];
    assign Y3 = D & ~S[2] &  S[1] &  S[0];

    assign Y4 = D &  S[2] & ~S[1] & ~S[0];
    assign Y5 = D &  S[2] & ~S[1] &  S[0];
    assign Y6 = D &  S[2] &  S[1] & ~S[0];
    assign Y7 = D &  S[2] &  S[1] &  S[0];
endmodule


/*output
meenakshi@meenakshi-Inspiron-3501:~/verilog/demux1to8$ vvp demux1to8.out
VCD info: dumpfile demux1to8.vcd opened for output.
$time=0|D=0|S=000|Y0=0|Y1=0|Y2=0|Y3=0|Y4=0|Y5=0|Y6=0|Y7=0
$time=10|D=1|S=000|Y0=1|Y1=0|Y2=0|Y3=0|Y4=0|Y5=0|Y6=0|Y7=0
$time=20|D=0|S=001|Y0=0|Y1=0|Y2=0|Y3=0|Y4=0|Y5=0|Y6=0|Y7=0
$time=30|D=1|S=001|Y0=0|Y1=1|Y2=0|Y3=0|Y4=0|Y5=0|Y6=0|Y7=0
$time=40|D=0|S=010|Y0=0|Y1=0|Y2=0|Y3=0|Y4=0|Y5=0|Y6=0|Y7=0
$time=50|D=1|S=010|Y0=0|Y1=0|Y2=1|Y3=0|Y4=0|Y5=0|Y6=0|Y7=0
$time=60|D=0|S=011|Y0=0|Y1=0|Y2=0|Y3=0|Y4=0|Y5=0|Y6=0|Y7=0
$time=70|D=1|S=011|Y0=0|Y1=0|Y2=0|Y3=1|Y4=0|Y5=0|Y6=0|Y7=0
$time=80|D=0|S=100|Y0=0|Y1=0|Y2=0|Y3=0|Y4=0|Y5=0|Y6=0|Y7=0
$time=90|D=1|S=100|Y0=0|Y1=0|Y2=0|Y3=0|Y4=1|Y5=0|Y6=0|Y7=0
$time=100|D=0|S=101|Y0=0|Y1=0|Y2=0|Y3=0|Y4=0|Y5=0|Y6=0|Y7=0
$time=110|D=1|S=101|Y0=0|Y1=0|Y2=0|Y3=0|Y4=0|Y5=1|Y6=0|Y7=0
$time=120|D=0|S=110|Y0=0|Y1=0|Y2=0|Y3=0|Y4=0|Y5=0|Y6=0|Y7=0
$time=130|D=1|S=110|Y0=0|Y1=0|Y2=0|Y3=0|Y4=0|Y5=0|Y6=1|Y7=0
$time=140|D=0|S=111|Y0=0|Y1=0|Y2=0|Y3=0|Y4=0|Y5=0|Y6=0|Y7=0
$time=150|D=1|S=111|Y0=0|Y1=0|Y2=0|Y3=0|Y4=0|Y5=0|Y6=0|Y7=1
demux1to8_tb.v:48: $finish called at 160 (1s)
*/

Day 5/Question 6/demux1to8_tb.v
module demux1to8_tb;
    reg  D;
    reg  [2:0] S;
    wire Y0, Y1, Y2, Y3, Y4, Y5, Y6, Y7;
  //instantiate
    demux1to8 DUT (
        .D(D),
        .S(S),
        .Y0(Y0), .Y1(Y1), .Y2(Y2), .Y3(Y3),
        .Y4(Y4), .Y5(Y5), .Y6(Y6), .Y7(Y7)
    );
    initial begin
        $monitor("$time=%0t|D=%b|S=%b|Y0=%b|Y1=%b|Y2=%b|Y3=%b|Y4=%b|Y5=%b|Y6=%b|Y7=%b",$time,D,S,Y0,Y1,Y2,Y3,Y4,Y5,Y6,Y7);
        $dumpfile("demux1to8.vcd");
        $dumpvars(0, demux1to8_tb);

        // S = 000
        D = 0; S = 3'b000; #10;
        D = 1; S = 3'b000; #10;

        // S = 001
        D = 0; S = 3'b001; #10;
        D = 1; S = 3'b001; #10;

        // S = 010
        D = 0; S = 3'b010; #10;
        D = 1; S = 3'b010; #10;

        // S = 011
        D = 0; S = 3'b011; #10;
        D = 1; S = 3'b011; #10;

        // S = 100
        D = 0; S = 3'b100; #10;
        D = 1; S = 3'b100; #10;

        // S = 101
        D = 0; S = 3'b101; #10;
        D = 1; S = 3'b101; #10;

        // S = 110
        D = 0; S = 3'b110; #10;
        D = 1; S = 3'b110; #10;

        // S = 111
        D = 0; S = 3'b111; #10;
        D = 1; S = 3'b111; #10;
        $finish;
    end
endmodule

Day 5/Question 6/demux1to8.vcd
$date
	Tue Dec 16 00:20:36 2025
$end
$version
	Icarus Verilog
$end
$timescale
	1s
$end
$scope module demux1to8_tb $end
$var wire 1 ! Y7 $end
$var wire 1 " Y6 $end
$var wire 1 # Y5 $end
$var wire 1 $ Y4 $end
$var wire 1 % Y3 $end
$var wire 1 & Y2 $end
$var wire 1 ' Y1 $end
$var wire 1 ( Y0 $end
$var reg 1 ) D $end
$var reg 3 * S [2:0] $end
$scope module DUT $end
$var wire 1 ) D $end
$var wire 3 + S [2:0] $end
$var wire 1 ( Y0 $end
$var wire 1 ' Y1 $end
$var wire 1 & Y2 $end
$var wire 1 % Y3 $end
$var wire 1 $ Y4 $end
$var wire 1 # Y5 $end
$var wire 1 " Y6 $end
$var wire 1 ! Y7 $end
$upscope $end
$upscope $end
$enddefinitions $end
$comment Show the parameter values. $end
$dumpall
$end
#0
$dumpvars
b0 +
b0 *
0)
0(
0'
0&
0%
0$
0#
0"
0!
$end
#10
1(
1)
#20
0(
b1 *
b1 +
0)
#30
1'
1)
#40
0'
b10 *
b10 +
0)
#50
1&
1)
#60
0&
b11 *
b11 +
0)
#70
1%
1)
#80
0%
b100 *
b100 +
0)
#90
1$
1)
#100
0$
b101 *
b101 +
0)
#110
1#
1)
#120
0#
b110 *
b110 +
0)
#130
1"
1)
#140
0"
b111 *
b111 +
0)
#150
1!
1)
