apb/slave.v
module apb_slave (
  input PCLK,
  input PRESETn,
  input [7:0] PADDR,
  input [7:0] PWDATA,
  input PWRITE,
  input PSEL,
  input PENABLE,

  output reg [7:0] PRDATA,
  output reg PREADY
);
  reg [7:0] mem [0:255];
  always @(posedge PCLK or negedge PRESETn) begin
   if (!PRESETn) begin
    PREADY <= 0;
   end
   else begin
   if (PSEL && PENABLE) begin
    PREADY <= 1;
   if (PWRITE)
    mem[PADDR] <= PWDATA;      
   else
    PRDATA <= mem[PADDR];     
   end
   else begin
    PREADY <= 0;
  end
  end
  end
endmodule

apb/master.v
module apb_master (
  input PCLK,
  input PRESETn,
  input transfer,        
  input read_write,    
  input  [7:0] write_addr,
  input  [7:0] write_data,
  input  [7:0] read_addr,
  input  [7:0] PRDATA,
  input  PREADY,

  output reg PWRITE,
  output reg PSEL,
  output reg PENABLE,
  output reg [7:0] PADDR,
  output reg [7:0] PWDATA,
  output reg [7:0] read_data_out
);
   reg [1:0] state;
   parameter IDLE = 2'b00,
              SETUP = 2'b01,
              ENABLE = 2'b10;

    always @(posedge PCLK or negedge PRESETn) begin
        if (!PRESETn) begin
            state <= IDLE;
            PSEL <= 0;
            PENABLE <= 0;
        end
        else begin

        case (state)

      IDLE: begin
        if (transfer) begin
         PSEL <= 1;
         PENABLE <= 0;
         state <= SETUP;
        if (read_write) begin
         PWRITE <= 1;
         PADDR  <= write_addr;
         PWDATA <= write_data;
        end
        else begin
         PWRITE <= 0;
         PADDR  <= read_addr;
        end
        end
        end

      SETUP: begin
         PENABLE <= 1;
         state <= ENABLE;
         end

      ENABLE: begin
       if (PREADY) begin
       if (!PWRITE)
        read_data_out <= PRDATA;
        PSEL <= 0;
        PENABLE <= 0;
        state <= IDLE;
     end
     end
       endcase
     end
     end
endmodule

apb/topmodule.v
module apb_top (
 input PCLK,
 input PRESETn,
 input transfer,
 input read_write,
 input  [7:0] write_addr,
 input  [7:0] write_data,
 input  [7:0] read_addr,
 output [7:0] read_data_out
);
 wire [7:0] PADDR;
 wire [7:0] PWDATA;
 wire [7:0] PRDATA;
 wire PWRITE, PSEL, PENABLE, PREADY;

    apb_master master (
     PCLK, PRESETn, transfer, read_write,write_addr, write_data, read_addr,PRDATA, PREADY,PWRITE,PSEL, PENABLE,PADDR, PWDATA, read_data_out
    );

    apb_slave slave (
     PCLK, PRESETn,PADDR, PWDATA, PWRITE,PSEL, PENABLE,PRDATA, PREADY
    );
endmodule

apb/testbench.v
module tb;
 reg PCLK;
 reg PRESETn;
 reg transfer;
 reg read_write;
 reg [7:0] write_addr;
 reg [7:0] write_data;
 reg [7:0] read_addr;
 wire [7:0] read_data_out;
  apb_top dut ( 
   PCLK, PRESETn, transfer, read_write,write_addr, write_data, read_addr,read_data_out
    );
 always #5 PCLK = ~PCLK;
 initial begin
   $dumpfile("apb.vcd");
   $dumpvars(0, tb);
   PCLK = 0;
   PRESETn = 0;
   transfer = 0;
    #20 
    PRESETn = 1;
    #10;
    read_write = 1;
    write_addr = 8'd20;
    write_data = 8'hA5;
    transfer = 1;
    #10
    transfer = 0;
    read_write = 0;
    read_addr = 8'd20;
    transfer = 1;
    #10 
    transfer = 0;
    #50;
    $display("Read Data = %h", read_data_out);
    #20 $finish;
   end
endmodule

apb/apb.vcd
$date
	Mon Feb 16 10:13:43 2026
$end
$version
	Icarus Verilog
$end
$timescale
	1s
$end
$scope module tb $end
$var wire 8 ! read_data_out [7:0] $end
$var reg 1 " PCLK $end
$var reg 1 # PRESETn $end
$var reg 8 $ read_addr [7:0] $end
$var reg 1 % read_write $end
$var reg 1 & transfer $end
$var reg 8 ' write_addr [7:0] $end
$var reg 8 ( write_data [7:0] $end
$scope module dut $end
$var wire 1 " PCLK $end
$var wire 1 # PRESETn $end
$var wire 8 ) read_addr [7:0] $end
$var wire 1 % read_write $end
$var wire 1 & transfer $end
$var wire 8 * write_addr [7:0] $end
$var wire 8 + write_data [7:0] $end
$var wire 8 , read_data_out [7:0] $end
$var wire 1 - PWRITE $end
$var wire 8 . PWDATA [7:0] $end
$var wire 1 / PSEL $end
$var wire 1 0 PREADY $end
$var wire 8 1 PRDATA [7:0] $end
$var wire 1 2 PENABLE $end
$var wire 8 3 PADDR [7:0] $end
$scope module master $end
$var wire 1 " PCLK $end
$var wire 1 # PRESETn $end
$var wire 8 4 read_addr [7:0] $end
$var wire 1 % read_write $end
$var wire 1 & transfer $end
$var wire 8 5 write_addr [7:0] $end
$var wire 8 6 write_data [7:0] $end
$var wire 1 0 PREADY $end
$var wire 8 7 PRDATA [7:0] $end
$var parameter 2 8 ENABLE $end
$var parameter 2 9 IDLE $end
$var parameter 2 : SETUP $end
$var reg 8 ; PADDR [7:0] $end
$var reg 1 2 PENABLE $end
$var reg 1 / PSEL $end
$var reg 8 < PWDATA [7:0] $end
$var reg 1 - PWRITE $end
$var reg 8 = read_data_out [7:0] $end
$var reg 2 > state [1:0] $end
$upscope $end
$scope module slave $end
$var wire 8 ? PADDR [7:0] $end
$var wire 1 " PCLK $end
$var wire 1 2 PENABLE $end
$var wire 1 # PRESETn $end
$var wire 1 / PSEL $end
$var wire 8 @ PWDATA [7:0] $end
$var wire 1 - PWRITE $end
$var reg 8 A PRDATA [7:0] $end
$var reg 1 0 PREADY $end
$upscope $end
$upscope $end
$upscope $end
$enddefinitions $end
$comment Show the parameter values. $end
$dumpall
b1 :
b0 9
b10 8
$end
#0
$dumpvars
bx A
bx @
bx ?
b0 >
bx =
bx <
bx ;
bx 7
bx 6
bx 5
bx 4
bx 3
02
bx 1
00
0/
bx .
x-
bx ,
bx +
bx *
bx )
bx (
bx '
0&
x%
bx $
0#
0"
bx !
$end
#5
1"
#10
0"
#15
1"
#20
0"
1#
#25
1"
#30
0"
1&
b10100101 (
b10100101 +
b10100101 6
b10100 '
b10100 *
b10100 5
1%
#35
b10100101 .
b10100101 <
b10100101 @
b10100 3
b10100 ;
b10100 ?
1-
b1 >
1/
1"
#40
0"
0&
#45
b10 >
12
1"
#50
0"
#55
10
1"
#60
0"
#65
b0 >
02
0/
1"
#70
0"
#75
00
1"
#80
0"
1&
b10100 $
b10100 )
b10100 4
0%
#85
0-
b1 >
1/
1"
#90
0"
0&
#95
b10 >
12
1"
#100
0"
#105
b10100101 1
b10100101 7
b10100101 A
10
1"
#110
0"
#115
b0 >
02
0/
b10100101 !
b10100101 ,
b10100101 =
1"
#120
0"
#125
00
1"
