Day 6/Question 1/parity_generator.v
module parity_generator (
    input  [3:0] D,
    input  mode,   
    output reg   P
);
    always @(*) begin
        if (mode == 1'b0)
            P = ^D;     
        else
            P = ~^D;     
    end
endmodule


/*output
meenakshi@meenakshi-Inspiron-3501:~/verilog/parity_generator$ vvp parity_generator.out
VCD info: dumpfile parity_generator.vcd opened for output.
$time=0|D=0000|mode=0|P=0
$time=10|D=0001|mode=0|P=1
$time=20|D=1011|mode=0|P=1
$time=30|D=1111|mode=0|P=0
$time=40|D=0000|mode=1|P=1
$time=50|D=0001|mode=1|P=0
$time=60|D=1011|mode=1|P=0
$time=70|D=1111|mode=1|P=1
parity_generator_tb.v:29: $finish called at 80 (1s)
*/

Day 6/Question 2/parity_generator_tb.v
module parity_generator_tb;
    reg  [3:0] D;
    reg        mode;
    wire       P;
    //instantiate 
    parity_generator dut (
        .D(D),
        .mode(mode),
        .P(P)
    );
    initial begin
        $monitor("$time=%0t|D=%b|mode=%b|P=%b",$time,D,mode,P);
        $dumpfile("parity_generator.vcd");
        $dumpvars(0, parity_generator_tb);

        mode = 0;
        D = 4'b0000; #10;  
        D = 4'b0001; #10;   
        D = 4'b1011; #10;   
        D = 4'b1111; #10;  

    
        mode = 1;
        D = 4'b0000; #10;   
        D = 4'b0001; #10;   
        D = 4'b1011; #10;  
        D = 4'b1111; #10;   

        $finish;
    end

endmodule

Day 6/Question 1/parity_generator.vcd
$date
	Wed Dec 17 11:35:33 2025
$end
$version
	Icarus Verilog
$end
$timescale
	1s
$end
$scope module parity_generator_tb $end
$var wire 1 ! P $end
$var reg 4 " D [3:0] $end
$var reg 1 # mode $end
$scope module dut $end
$var wire 4 $ D [3:0] $end
$var wire 1 # mode $end
$var reg 1 ! P $end
$upscope $end
$upscope $end
$enddefinitions $end
$comment Show the parameter values. $end
$dumpall
$end
#0
$dumpvars
b0 $
0#
b0 "
0!
$end
#10
1!
b1 "
b1 $
#20
b1011 "
b1011 $
#30
0!
b1111 "
b1111 $
#40
1!
b0 "
b0 $
1#
#50
0!
b1 "
b1 $
#60
b1011 "
b1011 $
#70
1!
b1111 "
b1111 $
