FSM/mealy machine/Question 2/nonoverlappingsequence101.v
module nonoverlappingsequence101 (
    input clk,
    input rst_n,
    input x,
    output reg z
);
parameter A = 2'b00;
parameter B = 2'b01;
parameter C = 2'b10;
reg [1:0] state, next_state;
always @(posedge clk or negedge rst_n) begin
    if (!rst_n)
        state <= A;
    else
        state <= next_state;
end
always @(*) begin
   case (state)
      A: begin
        if (x)
          next_state = B;
        else
          next_state = A;
        end
      B: begin
        if (!x)
          next_state = C;
        else
          next_state = B;
        end
      C: begin
        if (x)
          next_state = A;   
        else
          next_state = A;
        end
        default: next_state = A;
endcase
end
always @(*) begin
    if (state == C && x)
        z = 1;
    else
        z = 0;
end
endmodule


/*output
meenakshi@meenakshi-Inspiron-3501:~/verilog/nonoverlappingsequence101$ vvp nonoverlappingsequence101.out
VCD info: dumpfile nonoverlappingsequence101.vcd opened for output.
$time=0 | x=0 | z=0
$time=22 | x=1 | z=0
$time=32 | x=0 | z=0
$time=42 | x=1 | z=1
$time=45 | x=1 | z=0
$time=52 | x=0 | z=0
$time=62 | x=1 | z=0
$time=82 | x=0 | z=0
$time=92 | x=1 | z=1
$time=95 | x=1 | z=0
nonoverlappingsequence101_tb.v:30: $finish called at 112 (1s)
*/

FSM/mealy machine/Question 2/nonoverlappingsequence101_tb.v
module nonoverlappingsequence101_tb;
reg clk;
reg rst_n;
reg x;
wire z;
nonoverlappingsequence101 dut (
    .clk(clk),
    .rst_n(rst_n),
    .x(x),
    .z(z)
);
always #5 clk = ~clk;
initial begin
$monitor("$time=%0t | x=%b | z=%b", $time, x, z);
$dumpfile("nonoverlappingsequence101.vcd");
$dumpvars(0, nonoverlappingsequence101_tb);
  clk = 0;
  rst_n = 0;
  x = 0;
  #12 rst_n = 1;
 // Input: 1 0 1 0 1 1 0 1
   #10 x = 1;
   #10 x = 0;
   #10 x = 1;  
   #10 x = 0;
   #10 x = 1;
   #10 x = 1;
   #10 x = 0;
   #10 x = 1;  
   #20 $finish;
end
endmodule

FSM/mealy machine/Question 2/nonoverlappingsequence101.vcd
$date
	Mon Dec 29 00:20:04 2025
$end
$version
	Icarus Verilog
$end
$timescale
	1s
$end
$scope module nonoverlappingsequence101_tb $end
$var wire 1 ! z $end
$var reg 1 " clk $end
$var reg 1 # rst_n $end
$var reg 1 $ x $end
$scope module dut $end
$var wire 1 " clk $end
$var wire 1 # rst_n $end
$var wire 1 $ x $end
$var parameter 2 % A $end
$var parameter 2 & B $end
$var parameter 2 ' C $end
$var reg 2 ( next_state [1:0] $end
$var reg 2 ) state [1:0] $end
$var reg 1 ! z $end
$upscope $end
$upscope $end
$enddefinitions $end
$comment Show the parameter values. $end
$dumpall
b10 '
b1 &
b0 %
$end
#0
$dumpvars
b0 )
b0 (
0$
0#
0"
0!
$end
#5
1"
#10
0"
#12
1#
#15
1"
#20
0"
#22
b1 (
1$
#25
b1 )
1"
#30
0"
#32
b10 (
0$
#35
b0 (
b10 )
1"
#40
0"
#42
1!
1$
#45
b1 (
0!
b0 )
1"
#50
0"
#52
b0 (
0$
#55
1"
#60
0"
#62
b1 (
1$
#65
b1 )
1"
#70
0"
#75
1"
#80
0"
#82
b10 (
0$
#85
b0 (
b10 )
1"
#90
0"
#92
1!
1$
#95
0!
b1 (
b0 )
1"
#100
0"
#105
b1 )
1"
