Day_11/Question 5/synchronousupdowncounter.v
module synchronousupdowncounter (
    input clk,
    input rst,
    input dir,
    output reg [3:0] q
);
always @(posedge clk or posedge rst) begin
   if (rst)
      q <= 4'b0000;
   else if (dir)
      q <= q + 1;  
   else
      q <= q - 1;  
end
endmodule


/*output
meenakshi@meenakshi-Inspiron-3501:~/verilog/synchronousupdowncounter$ vvp synchronousupdowncounter.out
VCD info: dumpfile synchronousupdowncounter.vcd opened for output.
time=0 dir=1 q=0000
time=15 dir=1 q=0001
time=25 dir=1 q=0010
time=35 dir=1 q=0011
time=45 dir=1 q=0100
time=50 dir=0 q=0100
time=55 dir=0 q=0011
time=65 dir=0 q=0010
time=75 dir=0 q=0001
time=85 dir=0 q=0000
time=90 dir=1 q=0000
time=95 dir=1 q=0001
time=105 dir=1 q=0010
time=115 dir=1 q=0011
time=125 dir=1 q=0100
time=135 dir=1 q=0101
time=145 dir=1 q=0110
time=155 dir=1 q=0111
time=165 dir=1 q=1000
time=175 dir=1 q=1001
time=185 dir=1 q=1010
synchronousupdowncounter_tb.v:21: $finish called at 190 (1s)
*/

Day_11/Question 5/synchronousupdowncounter_tb.v
module synchronousupdowncounter_tb;
 reg clk, rst, dir;
 wire [3:0] q;
 synchronousupdowncounter dut (
        .clk(clk),
        .rst(rst),
        .dir(dir),
        .q(q)
    );
always #5 clk = ~clk;
initial begin
$monitor("time=%0t dir=%b q=%b", $time, dir, q);
$dumpfile("synchronousupdowncounter.vcd");
$dumpvars(0, synchronousupdowncounter_tb);
    clk = 0;
    rst = 1;
    dir = 1;   
    #10 rst = 0;
    #40 dir = 0; 
    #40 dir = 1; 
    #100 $finish;
 end
 endmodule

Day_11/Question 5/synchronousupdowncounter.vcd
$date
	Sun Dec 28 01:05:15 2025
$end
$version
	Icarus Verilog
$end
$timescale
	1s
$end
$scope module synchronousupdowncounter_tb $end
$var wire 4 ! q [3:0] $end
$var reg 1 " clk $end
$var reg 1 # dir $end
$var reg 1 $ rst $end
$scope module dut $end
$var wire 1 " clk $end
$var wire 1 # dir $end
$var wire 1 $ rst $end
$var reg 4 % q [3:0] $end
$upscope $end
$upscope $end
$enddefinitions $end
$comment Show the parameter values. $end
$dumpall
$end
#0
$dumpvars
b0 %
1$
1#
0"
b0 !
$end
#5
1"
#10
0"
0$
#15
b1 !
b1 %
1"
#20
0"
#25
b10 !
b10 %
1"
#30
0"
#35
b11 !
b11 %
1"
#40
0"
#45
b100 !
b100 %
1"
#50
0"
0#
#55
b11 !
b11 %
1"
#60
0"
#65
b10 !
b10 %
1"
#70
0"
#75
b1 !
b1 %
1"
#80
0"
#85
b0 !
b0 %
1"
#90
0"
1#
#95
b1 !
b1 %
1"
#100
0"
#105
b10 !
b10 %
1"
#110
0"
#115
b11 !
b11 %
1"
#120
0"
#125
b100 !
b100 %
1"
#130
0"
#135
b101 !
b101 %
1"
#140
0"
#145
b110 !
b110 %
1"
#150
0"
#155
b111 !
b111 %
1"
#160
0"
#165
b1000 !
b1000 %
1"
#170
0"
#175
b1001 !
b1001 %
1"
#180
0"
#185
b1010 !
b1010 %
1"
