Day_11/Question 4/synchronousdowncounter.v
module synchronousdowncounter (
  input clk,
  input rst,
  output reg [3:0] q
);
always @(posedge clk or posedge rst) begin
   if (rst)
     q <= 4'b1111;  
   else
     q <= q - 1;
end
endmodule




/*output
meenakshi@meenakshi-Inspiron-3501:~/verilog/synchronousdowncounter$ vvp synchronousdowncounter.out
VCD info: dumpfile synchronousdowncounter.vcd opened for output.
time=0 | q=1111
time=15 | q=1110
time=25 | q=1101
time=35 | q=1100
time=45 | q=1011
time=55 | q=1010
time=65 | q=1001
time=75 | q=1000
time=85 | q=0111
time=95 | q=0110
time=105 | q=0101
synchronousdowncounter_tb.v:17: $finish called at 110 (1s)
*/

Day_11/Question 4/synchronousdowncounter_tb.v
module synchronousdowncounter_tb;
 reg clk, rst;
 wire [3:0] q;
 synchronousdowncounter dut (
    .clk(clk),
    .rst(rst),
    .q(q)
);
always #5 clk = ~clk;
initial begin
$monitor("time=%0t | q=%b", $time, q);
$dumpfile("synchronousdowncounter.vcd");
$dumpvars(0, synchronousdowncounter_tb);
   clk = 0;
   rst = 1;
   #10 rst = 0;
   #100 $finish;
end
endmodule

Day_11/Question 4/synchronousdowncounter.vcd
$date
	Sun Dec 28 00:42:53 2025
$end
$version
	Icarus Verilog
$end
$timescale
	1s
$end
$scope module synchronousdowncounter_tb $end
$var wire 4 ! q [3:0] $end
$var reg 1 " clk $end
$var reg 1 # rst $end
$scope module dut $end
$var wire 1 " clk $end
$var wire 1 # rst $end
$var reg 4 $ q [3:0] $end
$upscope $end
$upscope $end
$enddefinitions $end
$comment Show the parameter values. $end
$dumpall
$end
#0
$dumpvars
b1111 $
1#
0"
b1111 !
$end
#5
1"
#10
0"
0#
#15
b1110 !
b1110 $
1"
#20
0"
#25
b1101 !
b1101 $
1"
#30
0"
#35
b1100 !
b1100 $
1"
#40
0"
#45
b1011 !
b1011 $
1"
#50
0"
#55
b1010 !
b1010 $
1"
#60
0"
#65
b1001 !
b1001 $
1"
#70
0"
#75
b1000 !
b1000 $
1"
#80
0"
#85
b111 !
b111 $
1"
#90
0"
#95
b110 !
b110 $
1"
#100
0"
#105
b101 !
b101 $
1"
