Day 7/Question 1/mux16to1using4to1.v
module mux4to1 (
    input  i0, i1, i2, i3,
    input  s0, s1,
    output y
);
    assign y = s1 ? (s0 ? i3 : i2)
                  : (s0 ? i1 : i0);
endmodule
module mux16to1using4to1 (
    input  i0,  i1,  i2,  i3,
    input  i4,  i5,  i6,  i7,
    input  i8,  i9,  i10, i11,
    input  i12, i13, i14, i15,
    input  s0, s1, s2, s3,
    output y
);

    wire w0, w1, w2, w3;
    mux4to1 m0 (i0,  i1,  i2,  i3,  s0, s1, w0);
    mux4to1 m1 (i4,  i5,  i6,  i7,  s0, s1, w1);
    mux4to1 m2 (i8,  i9,  i10, i11, s0, s1, w2);
    mux4to1 m3 (i12, i13, i14, i15, s0, s1, w3);

    mux4to1 m4 (w0, w1, w2, w3, s2, s3, y);

endmodule

Day 7/Question 1/mux16to1using4to1_tb.v
module mux16to1using4to1_tb;
    reg  i0,  i1,  i2,  i3;
    reg  i4,  i5,  i6,  i7;
    reg  i8,  i9,  i10, i11;
    reg  i12, i13, i14, i15;
    reg  s0, s1, s2, s3;
    wire y;
    //instantiate
    mux16to1using4to1 dut (
        .i0(i0),   .i1(i1),   .i2(i2),   .i3(i3),
        .i4(i4),   .i5(i5),   .i6(i6),   .i7(i7),
        .i8(i8),   .i9(i9),   .i10(i10), .i11(i11),
        .i12(i12), .i13(i13), .i14(i14), .i15(i15),
        .s0(s0), .s1(s1), .s2(s2), .s3(s3),
        .y(y)
    );
    initial begin
        $monitor("t=%0t | s3s2s1s0=%b%b%b%b | y=%b",$time, s3, s2, s1, s0, y);
        $dumpfile("mux16to1using4to1.vcd");
        $dumpvars(0, mux16to1using4to1_tb);

        i0=0;  i1=1;  i2=0;  i3=1;
        i4=1;  i5=0;  i6=1;  i7=0;
        i8=0;  i9=1;  i10=0; i11=1;
        i12=1; i13=0; i14=1; i15=0;

        {s3,s2,s1,s0} = 4'b0000; #10;  
        {s3,s2,s1,s0} = 4'b0001; #10; 
        {s3,s2,s1,s0} = 4'b0010; #10;  
        {s3,s2,s1,s0} = 4'b0011; #10;  

        {s3,s2,s1,s0} = 4'b0100; #10;  
        {s3,s2,s1,s0} = 4'b0101; #10; 
        {s3,s2,s1,s0} = 4'b0110; #10;  
        {s3,s2,s1,s0} = 4'b0111; #10;  

        {s3,s2,s1,s0} = 4'b1000; #10;  
        {s3,s2,s1,s0} = 4'b1001; #10;  
        {s3,s2,s1,s0} = 4'b1010; #10;  
        {s3,s2,s1,s0} = 4'b1011; #10;  

        {s3,s2,s1,s0} = 4'b1100; #10;  
        {s3,s2,s1,s0} = 4'b1101; #10;  
        {s3,s2,s1,s0} = 4'b1110; #10;  
        {s3,s2,s1,s0} = 4'b1111; #10;  

        $finish;
    end
endmodule

Day 7/Question 1/mux16to1using4to1.vcd
$date
	Thu Dec 18 14:34:02 2025
$end
$version
	Icarus Verilog
$end
$timescale
	1s
$end
$scope module mux16to1using4to1_tb $end
$var wire 1 ! y $end
$var reg 1 " i0 $end
$var reg 1 # i1 $end
$var reg 1 $ i10 $end
$var reg 1 % i11 $end
$var reg 1 & i12 $end
$var reg 1 ' i13 $end
$var reg 1 ( i14 $end
$var reg 1 ) i15 $end
$var reg 1 * i2 $end
$var reg 1 + i3 $end
$var reg 1 , i4 $end
$var reg 1 - i5 $end
$var reg 1 . i6 $end
$var reg 1 / i7 $end
$var reg 1 0 i8 $end
$var reg 1 1 i9 $end
$var reg 1 2 s0 $end
$var reg 1 3 s1 $end
$var reg 1 4 s2 $end
$var reg 1 5 s3 $end
$scope module dut $end
$var wire 1 " i0 $end
$var wire 1 # i1 $end
$var wire 1 $ i10 $end
$var wire 1 % i11 $end
$var wire 1 & i12 $end
$var wire 1 ' i13 $end
$var wire 1 ( i14 $end
$var wire 1 ) i15 $end
$var wire 1 * i2 $end
$var wire 1 + i3 $end
$var wire 1 , i4 $end
$var wire 1 - i5 $end
$var wire 1 . i6 $end
$var wire 1 / i7 $end
$var wire 1 0 i8 $end
$var wire 1 1 i9 $end
$var wire 1 2 s0 $end
$var wire 1 3 s1 $end
$var wire 1 4 s2 $end
$var wire 1 5 s3 $end
$var wire 1 ! y $end
$var wire 1 6 w3 $end
$var wire 1 7 w2 $end
$var wire 1 8 w1 $end
$var wire 1 9 w0 $end
$scope module m0 $end
$var wire 1 " i0 $end
$var wire 1 # i1 $end
$var wire 1 * i2 $end
$var wire 1 + i3 $end
$var wire 1 2 s0 $end
$var wire 1 3 s1 $end
$var wire 1 9 y $end
$upscope $end
$scope module m1 $end
$var wire 1 , i0 $end
$var wire 1 - i1 $end
$var wire 1 . i2 $end
$var wire 1 / i3 $end
$var wire 1 2 s0 $end
$var wire 1 3 s1 $end
$var wire 1 8 y $end
$upscope $end
$scope module m2 $end
$var wire 1 0 i0 $end
$var wire 1 1 i1 $end
$var wire 1 $ i2 $end
$var wire 1 % i3 $end
$var wire 1 2 s0 $end
$var wire 1 3 s1 $end
$var wire 1 7 y $end
$upscope $end
$scope module m3 $end
$var wire 1 & i0 $end
$var wire 1 ' i1 $end
$var wire 1 ( i2 $end
$var wire 1 ) i3 $end
$var wire 1 2 s0 $end
$var wire 1 3 s1 $end
$var wire 1 6 y $end
$upscope $end
$scope module m4 $end
$var wire 1 9 i0 $end
$var wire 1 8 i1 $end
$var wire 1 7 i2 $end
$var wire 1 6 i3 $end
$var wire 1 4 s0 $end
$var wire 1 5 s1 $end
$var wire 1 ! y $end
$upscope $end
$upscope $end
$upscope $end
$enddefinitions $end
$comment Show the parameter values. $end
$dumpall
$end
#0
$dumpvars
09
18
07
16
05
04
03
02
11
00
0/
1.
0-
1,
1+
0*
0)
1(
0'
1&
1%
0$
1#
0"
0!
$end
#10
1!
19
08
17
06
12
#20
0!
09
18
07
16
13
02
#30
1!
19
08
17
06
12
#40
09
18
07
16
14
03
02
#50
0!
19
08
17
06
12
#60
1!
09
18
07
16
13
02
#70
0!
19
08
17
06
12
#80
09
18
07
16
15
04
03
02
#90
1!
19
08
17
06
12
#100
0!
09
18
07
16
13
02
#110
1!
19
08
17
06
12
#120
09
18
07
16
14
03
02
#130
0!
19
08
17
06
12
#140
1!
09
18
07
16
13
02
#150
0!
19
08
17
06
12
