Day 9/Question 5/sipo.v
module sipo(
 input clk,
 input rst,
 input serial_in,
 output reg [3:0] parallel_out
);
always @(posedge clk or posedge rst) begin
     if (rst)
      parallel_out <= 4'b0000;
     else
      parallel_out <= {parallel_out[2:0], serial_in};
end
endmodule


/*output
meenakshi@meenakshi-Inspiron-3501:~/verilog/sipo$ vvp sipo.out
VCD info: dumpfile sipo.vcd opened for output.
$time=0| clk=0|rst=1| serial_in=0| parallel_out=0000
$time=5| clk=1|rst=1| serial_in=0| parallel_out=0000
$time=10| clk=0|rst=0| serial_in=0| parallel_out=0000
$time=15| clk=1|rst=0| serial_in=0| parallel_out=0000
$time=20| clk=0|rst=0| serial_in=1| parallel_out=0000
$time=25| clk=1|rst=0| serial_in=1| parallel_out=0001
$time=30| clk=0|rst=0| serial_in=0| parallel_out=0001
$time=35| clk=1|rst=0| serial_in=0| parallel_out=0010
$time=40| clk=0|rst=0| serial_in=1| parallel_out=0010
$time=45| clk=1|rst=0| serial_in=1| parallel_out=0101
$time=50| clk=0|rst=0| serial_in=1| parallel_out=0101
$time=55| clk=1|rst=0| serial_in=1| parallel_out=1011
$time=60| clk=0|rst=0| serial_in=1| parallel_out=1011
$time=65| clk=1|rst=0| serial_in=1| parallel_out=0111
sipo_tb.v:16: $finish called at 70 (1s)
$time=70| clk=0|rst=0| serial_in=1| parallel_out=0111
meenakshi@meenakshi-Inspiron-3501:~/verilog/sipo$ gtkw
*/

Day 9/Question 5/sipo_tb.v
module sipo_tb;
  reg clk, rst, serial_in;
  wire [3:0] parallel_out;
sipo dut (clk, rst, serial_in, parallel_out);
 always #5 clk = ~clk;
initial begin
    $monitor("$time=%0t| clk=%b|rst=%b| serial_in=%b| parallel_out=%b",$time,clk,rst,serial_in,parallel_out);
    $dumpfile("sipo.vcd");
    $dumpvars(0,sipo_tb);
 clk = 0; rst = 1; serial_in = 0;
 #10 rst = 0;
 #10 serial_in = 1;
 #10 serial_in = 0;
 #10 serial_in = 1;
 #10 serial_in = 1;
 #20 $finish;
end
endmodule

Day 9/Question 5/sipo.vcd
$date
	Sat Dec 27 12:54:54 2025
$end
$version
	Icarus Verilog
$end
$timescale
	1s
$end
$scope module sipo_tb $end
$var wire 4 ! parallel_out [3:0] $end
$var reg 1 " clk $end
$var reg 1 # rst $end
$var reg 1 $ serial_in $end
$scope module dut $end
$var wire 1 " clk $end
$var wire 1 # rst $end
$var wire 1 $ serial_in $end
$var reg 4 % parallel_out [3:0] $end
$upscope $end
$upscope $end
$enddefinitions $end
$comment Show the parameter values. $end
$dumpall
$end
#0
$dumpvars
b0 %
0$
1#
0"
b0 !
$end
#5
1"
#10
0"
0#
#15
1"
#20
0"
1$
#25
b1 !
b1 %
1"
#30
0"
0$
#35
b10 !
b10 %
1"
#40
0"
1$
#45
b101 !
b101 %
1"
#50
0"
#55
b1011 !
b1011 %
1"
#60
0"
#65
b111 !
b111 %
1"
