Day_11/Question 2/johnsoncounter.v
module johnson_counter (
    input clk,
    input rst,
    output reg [3:0] q
);
always @(posedge clk or posedge rst) begin
     if (rst)
       q <= 4'b0000;
     else
       q <= {q[2:0], ~q[3]};   
    end
endmodule




/*output
meenakshi@meenakshi-Inspiron-3501:~/verilog/johnsoncounter$ vvp johnsoncounter.out
VCD info: dumpfile johnsoncounter.vcd opened for output.
t=0 q=0000
t=15 q=0001
t=25 q=0011
t=35 q=0111
t=45 q=1111
t=55 q=1110
t=65 q=1100
t=75 q=1000
t=85 q=0000
t=95 q=0001
t=105 q=0011
johnsoncounter_tb.v:17: $finish called at 110 (1s)
*/

Day_11/Question 2/johnsoncounter_tb.v
module johnsoncounter_tb;
reg clk, rst;
wire [3:0] q;
johnson_counter dut (
   .clk(clk),
   .rst(rst),
   .q(q)
    );
always #5 clk = ~clk;
initial begin
$monitor("t=%0t q=%b", $time, q);
$dumpfile("johnsoncounter.vcd");
$dumpvars(0, johnsoncounter_tb);
clk = 0;
rst = 1;
#10 rst = 0;
#100 $finish;
end
endmodule

Day_11/Question 2/johnsoncounter.vcd
$date
	Sat Dec 27 21:57:19 2025
$end
$version
	Icarus Verilog
$end
$timescale
	1s
$end
$scope module johnsoncounter_tb $end
$var wire 4 ! q [3:0] $end
$var reg 1 " clk $end
$var reg 1 # rst $end
$scope module dut $end
$var wire 1 " clk $end
$var wire 1 # rst $end
$var reg 4 $ q [3:0] $end
$upscope $end
$upscope $end
$enddefinitions $end
$comment Show the parameter values. $end
$dumpall
$end
#0
$dumpvars
b0 $
1#
0"
b0 !
$end
#5
1"
#10
0"
0#
#15
b1 !
b1 $
1"
#20
0"
#25
b11 !
b11 $
1"
#30
0"
#35
b111 !
b111 $
1"
#40
0"
#45
b1111 !
b1111 $
1"
#50
0"
#55
b1110 !
b1110 $
1"
#60
0"
#65
b1100 !
b1100 $
1"
#70
0"
#75
b1000 !
b1000 $
1"
#80
0"
#85
b0 !
b0 $
1"
#90
0"
#95
b1 !
b1 $
1"
#100
0"
#105
b11 !
b11 $
1"
