Memory/Single Port Synchronous RAM/singleportsynchronousram.v
module singleportsynchronousram(
input clk,
input we,
input [3:0] addr,
input [7:0] din,
output reg [7:0] dout
);
reg[7:0] mem[0:15];
always @(posedge clk) begin
if(we) begin    
mem[addr]<=din;
dout<=din;
end
else begin 
dout<=mem[addr];
end
end
endmodule



/*output
meenakshi@meenakshi-Inspiron-3501:~/verilog/singleportsynchronousram$ vvp singleportsynchronousram.out
VCD info: dumpfile singleportsynchronousram.vcd opened for output.
$time=0|clk=0|we=0|addr=0000|din=00000000|dout=xxxxxxxx
$time=5|clk=1|we=0|addr=0000|din=00000000|dout=xxxxxxxx
$time=10|clk=0|we=1|addr=0010|din=10101010|dout=xxxxxxxx
$time=15|clk=1|we=1|addr=0010|din=10101010|dout=10101010
$time=20|clk=0|we=1|addr=0100|din=01010101|dout=10101010
$time=25|clk=1|we=1|addr=0100|din=01010101|dout=01010101
$time=30|clk=0|we=0|addr=0010|din=01010101|dout=01010101
$time=35|clk=1|we=0|addr=0010|din=01010101|dout=10101010
$time=40|clk=0|we=0|addr=0100|din=01010101|dout=10101010
$time=45|clk=1|we=0|addr=0100|din=01010101|dout=01010101
$time=50|clk=0|we=0|addr=0100|din=01010101|dout=01010101
$time=55|clk=1|we=0|addr=0100|din=01010101|dout=01010101
singleportsynchronousram_tb.v:37: $finish called at 60 (1s)
$time=60|clk=0|we=0|addr=0100|din=01010101|dout=01010101
*/

Memory/Single Port Synchronous RAM/singleportsynchronousram_tb.v
module singleportsynchronousram_tb;
reg clk;
reg we;
reg [3:0] addr;
reg [7:0] din;
wire [7:0] dout;
//instantiate 
singleportsynchronousram dut(
    .clk(clk),
    .we(we),
    .addr(addr),
    .din(din),
    .dout(dout)
);
always #5 clk=~clk;
initial begin
$monitor("$time=%0t|clk=%b|we=%b|addr=%b|din=%b|dout=%b",$time,clk,we,addr,din,dout);
$dumpfile("singleportsynchronousram.vcd");
$dumpvars(0,singleportsynchronousram_tb);
    clk = 0;
    we  = 0;
    addr = 0;
    din  = 0;
    #10;
    we = 1;
    addr = 4'b0010;
    din  = 8'hAA;   
     #10;
    addr = 4'b0100;
    din  = 8'h55;   
    #10;
    we = 0;
    addr = 4'b0010; 
    #10;
    addr = 4'b0100; 
    #20;
    $finish;
    end
endmodule

Memory/Single Port Synchronous RAM/singleportsynchronousram.vcd
$date
	Fri Jan  2 16:10:06 2026
$end
$version
	Icarus Verilog
$end
$timescale
	1s
$end
$scope module singleportsynchronousram_tb $end
$var wire 8 ! dout [7:0] $end
$var reg 4 " addr [3:0] $end
$var reg 1 # clk $end
$var reg 8 $ din [7:0] $end
$var reg 1 % we $end
$scope module dut $end
$var wire 4 & addr [3:0] $end
$var wire 1 # clk $end
$var wire 8 ' din [7:0] $end
$var wire 1 % we $end
$var reg 8 ( dout [7:0] $end
$upscope $end
$upscope $end
$enddefinitions $end
$comment Show the parameter values. $end
$dumpall
$end
#0
$dumpvars
bx (
b0 '
b0 &
0%
b0 $
0#
b0 "
bx !
$end
#5
1#
#10
0#
b10101010 $
b10101010 '
b10 "
b10 &
1%
#15
b10101010 !
b10101010 (
1#
#20
0#
b1010101 $
b1010101 '
b100 "
b100 &
#25
b1010101 !
b1010101 (
1#
#30
0#
b10 "
b10 &
0%
#35
b10101010 !
b10101010 (
1#
#40
0#
b100 "
b100 &
#45
b1010101 !
b1010101 (
1#
