Day 5/Question 9/decoder3to8.v
module decoder3to8(
    input A, B, C,
    output reg [7:0] Y
);
   always @(*) begin
    case ({A,B,C})
            3'b000: Y = 8'b00000001;
            3'b001: Y = 8'b00000010;
            3'b010: Y = 8'b00000100;
            3'b011: Y = 8'b00001000;
            3'b100: Y = 8'b00010000;
            3'b101: Y = 8'b00100000;
            3'b110: Y = 8'b01000000;
            3'b111: Y = 8'b10000000;
        endcase
    end
endmodule


/*output
meenakshi@meenakshi-Inspiron-3501:~/verilog/decoder3to8$ vvp decoder3to8.out
VCD info: dumpfile decoder3to8.vcd opened for output.
Time=0 | A=0 B=0 C=0 | Y=00000001
Time=10 | A=0 B=0 C=1 | Y=00000010
Time=20 | A=0 B=1 C=0 | Y=00000100
Time=30 | A=0 B=1 C=1 | Y=00001000
Time=40 | A=1 B=0 C=0 | Y=00010000
Time=50 | A=1 B=0 C=1 | Y=00100000
Time=60 | A=1 B=1 C=0 | Y=01000000
Time=70 | A=1 B=1 C=1 | Y=10000000
decoder3to8_tb.v:23: $finish called at 80 (1s)
*/

Day 5/Question 9/decoder3to8_tb.v
module decoder3to8_tb;
    reg A, B, C;
    wire [7:0] Y;
    //instantiate
    decoder3to8 dut (
        .A(A),
        .B(B),
        .C(C),
        .Y(Y)
    );
    initial begin
        $monitor("Time=%0t | A=%b B=%b C=%b | Y=%b",$time, A, B, C, Y);
        $dumpfile("decoder3to8.vcd");
        $dumpvars(0, decoder3to8_tb);
        A=0; B=0; C=0; #10;
        A=0; B=0; C=1; #10;
        A=0; B=1; C=0; #10;
        A=0; B=1; C=1; #10;
        A=1; B=0; C=0; #10;
        A=1; B=0; C=1; #10;
        A=1; B=1; C=0; #10;
        A=1; B=1; C=1; #10;
        $finish;
    end
endmodule

Day 5/Question 9/decoder3to8.vcd
$date
	Tue Dec 16 12:32:23 2025
$end
$version
	Icarus Verilog
$end
$timescale
	1s
$end
$scope module decoder3to8_tb $end
$var wire 8 ! Y [7:0] $end
$var reg 1 " A $end
$var reg 1 # B $end
$var reg 1 $ C $end
$scope module dut $end
$var wire 1 " A $end
$var wire 1 # B $end
$var wire 1 $ C $end
$var reg 8 % Y [7:0] $end
$upscope $end
$upscope $end
$enddefinitions $end
$comment Show the parameter values. $end
$dumpall
$end
#0
$dumpvars
b1 %
0$
0#
0"
b1 !
$end
#10
b10 !
b10 %
1$
#20
b100 !
b100 %
0$
1#
#30
b1000 !
b1000 %
1$
#40
b10000 !
b10000 %
0$
0#
1"
#50
b100000 !
b100000 %
1$
#60
b1000000 !
b1000000 %
0$
1#
#70
b10000000 !
b10000000 %
1$
