Day 1/Question 4/full_adder.v
module full_adder(input a,b,cin, output s,cout);
assign s= a ^ b ^ cin ;
assign cout= (a&b) | (b&cin) | (cin&a);
endmodule

Day 1/Question 4/full_adder_tb.v
module full_adder_tb;
	reg a,b,cin;
	wire s,cout;
	//instantiate
	full_adder dut(
		.a(a),
		.b(b),
		.cin(cin),
		.s(s),
		.cout(cout)
		);
	initial begin
	$dumpfile("full_adder.vcd");
	$dumpvars(0,full_adder_tb);
	$monitor("$time=%0t, a=%b b=%b cin=%b s=%b cout=%b",$time,a,b,cin,s,cout);
    	a=0;b=0;cin=0; #1
	a=0;b=0;cin=1; #1
	a=0;b=1;cin=0; #1
	a=0;b=1;cin=1; #1
	a=1;b=0;cin=0; #1
	a=1;b=0;cin=1; #1
	a=1;b=1;cin=0; #1
	a=1;b=1;cin=1; 
	$finish;
       end 
       endmodule

Day 1/Question 4/full_adder.vcd
$date
	Tue Dec  2 14:19:23 2025
$end
$version
	Icarus Verilog
$end
$timescale
	1s
$end
$scope module full_adder_tb $end
$var wire 1 ! s $end
$var wire 1 " cout $end
$var reg 1 # a $end
$var reg 1 $ b $end
$var reg 1 % cin $end
$scope module dut $end
$var wire 1 # a $end
$var wire 1 $ b $end
$var wire 1 % cin $end
$var wire 1 " cout $end
$var wire 1 ! s $end
$upscope $end
$upscope $end
$enddefinitions $end
$comment Show the parameter values. $end
$dumpall
$end
#0
$dumpvars
0%
0$
0#
0"
0!
$end
#1
1!
1%
#2
0%
1$
#3
1"
0!
1%
#4
0"
1!
0%
0$
1#
#5
1"
0!
1%
#6
0%
1$
#7
1!
1%
