Day_10/Question 1/piso.v
module piso (
    input clk,
    input rst,
    input load,
    input [3:0] parallel_in,
    output reg serial_out
);
reg [3:0] shift_reg;
always @(posedge clk or posedge rst) begin
  if (rst) begin
      shift_reg  <= 4'b0000;
      serial_out <= 1'b0;
  end
  else if (load) begin
      shift_reg <= parallel_in;  
  end
  else begin
      serial_out <= shift_reg[3]; 
      shift_reg  <= shift_reg << 1;
end
end
endmodule



/*output 
meenakshi@meenakshi-Inspiron-3501:~/verilog/piso$ vvp piso.out
VCD info: dumpfile piso.vcd opened for output.
$time=0| clk=0|rst=1| load=0|parallel_in=0000| serial_out=0
$time=5| clk=1|rst=1| load=0|parallel_in=0000| serial_out=0
$time=10| clk=0|rst=0| load=0|parallel_in=0000| serial_out=0
$time=15| clk=1|rst=0| load=0|parallel_in=0000| serial_out=0
$time=20| clk=0|rst=0| load=1|parallel_in=1011| serial_out=0
$time=25| clk=1|rst=0| load=1|parallel_in=1011| serial_out=0
$time=30| clk=0|rst=0| load=0|parallel_in=1011| serial_out=0
$time=35| clk=1|rst=0| load=0|parallel_in=1011| serial_out=1
$time=40| clk=0|rst=0| load=0|parallel_in=1011| serial_out=1
$time=45| clk=1|rst=0| load=0|parallel_in=1011| serial_out=0
$time=50| clk=0|rst=0| load=0|parallel_in=1011| serial_out=0
$time=55| clk=1|rst=0| load=0|parallel_in=1011| serial_out=1
$time=60| clk=0|rst=0| load=0|parallel_in=1011| serial_out=1
$time=65| clk=1|rst=0| load=0|parallel_in=1011| serial_out=1
piso_tb.v:28: $finish called at 70 (1s)
$time=70| clk=0|rst=0| load=0|parallel_in=1011| serial_out=1
*/

Day_10/Question 1/piso_tb.v
module piso_tb;
    reg clk;
    reg rst;
    reg load;
    reg [3:0] parallel_in;
    wire serial_out;
    piso dut (
        .clk(clk),
        .rst(rst),
        .load(load),
        .parallel_in(parallel_in),
        .serial_out(serial_out)
    );
    always #5 clk = ~clk;
    initial begin
        $monitor("$time=%0t| clk=%b|rst=%b| load=%b|parallel_in=%b| serial_out=%b", $time,clk,rst,load,parallel_in,serial_out);
        $dumpfile("piso.vcd");
        $dumpvars(0,piso_tb);
        clk = 0;
        rst = 1;
        load = 0;
        parallel_in = 4'b0000;
        #10 rst = 0;
        #10 load = 1;
        parallel_in = 4'b1011;
        #10 load = 0;
        #40;
        $finish;
    end
endmodule

Day_10/Question 1/piso.vcd
$date
	Sat Dec 27 13:08:09 2025
$end
$version
	Icarus Verilog
$end
$timescale
	1s
$end
$scope module piso_tb $end
$var wire 1 ! serial_out $end
$var reg 1 " clk $end
$var reg 1 # load $end
$var reg 4 $ parallel_in [3:0] $end
$var reg 1 % rst $end
$scope module dut $end
$var wire 1 " clk $end
$var wire 1 # load $end
$var wire 4 & parallel_in [3:0] $end
$var wire 1 % rst $end
$var reg 1 ! serial_out $end
$var reg 4 ' shift_reg [3:0] $end
$upscope $end
$upscope $end
$enddefinitions $end
$comment Show the parameter values. $end
$dumpall
$end
#0
$dumpvars
b0 '
b0 &
1%
b0 $
0#
0"
0!
$end
#5
1"
#10
0"
0%
#15
1"
#20
0"
b1011 $
b1011 &
1#
#25
b1011 '
1"
#30
0"
0#
#35
b110 '
1!
1"
#40
0"
#45
b1100 '
0!
1"
#50
0"
#55
b1000 '
1!
1"
#60
0"
#65
b0 '
1"
