Day 5/Question 2/mux2to1_bool.v
module mux2to1_bool (
    input A,
    input B,
    input S,
    output Y
);
    assign Y = (~S & A) | (S & B);
endmodule


/*OUTPUT
meenakshi@meenakshi-Inspiron-3501:~/verilog/mux2to1_bool$ vvp mux2to1_bool.out
VCD info: dumpfile mux2to1_bool.vcd opened for output.
$time=0|A=0|B=0|S=0|Y=0
$time=10|A=0|B=1|S=0|Y=0
$time=20|A=1|B=0|S=0|Y=1
$time=30|A=1|B=1|S=0|Y=1
$time=40|A=0|B=0|S=1|Y=0
$time=50|A=0|B=1|S=1|Y=1
$time=60|A=1|B=0|S=1|Y=0
$time=70|A=1|B=1|S=1|Y=1
mux2to1_bool_tb.v:24: $finish called at 80 (1s)
*/

Day 5/Question 2/mux2to1_bool_tb.v
module mux2to1_bool_tb;
    reg A, B, S;
    wire Y;
    //instantiate
    mux2to1_bool DUT (
        .A(A),
        .B(B),
        .S(S),
        .Y(Y)
    );
    initial begin
   $monitor("$time=%0t|A=%b|B=%b|S=%b|Y=%b",$time,A,B,S,Y);
   $dumpfile("mux2to1_bool.vcd");
   $dumpvars(0, mux2to1_bool_tb);
        A = 0; B = 0; S = 0; #10;
        A = 0; B = 1; S = 0; #10;
        A = 1; B = 0; S = 0; #10;
        A = 1; B = 1; S = 0; #10;

        A = 0; B = 0; S = 1; #10;
        A = 0; B = 1; S = 1; #10;
        A = 1; B = 0; S = 1; #10;
        A = 1; B = 1; S = 1; #10;
        $finish;
    end
endmodule

Day 5/Question 2/mux2to1_bool.vcd
$date
	Mon Dec 15 21:48:41 2025
$end
$version
	Icarus Verilog
$end
$timescale
	1s
$end
$scope module mux2to1_bool_tb $end
$var wire 1 ! Y $end
$var reg 1 " A $end
$var reg 1 # B $end
$var reg 1 $ S $end
$scope module DUT $end
$var wire 1 " A $end
$var wire 1 # B $end
$var wire 1 $ S $end
$var wire 1 ! Y $end
$upscope $end
$upscope $end
$enddefinitions $end
$comment Show the parameter values. $end
$dumpall
$end
#0
$dumpvars
0$
0#
0"
0!
$end
#10
1#
#20
1!
0#
1"
#30
1#
#40
0!
1$
0#
0"
#50
1!
1#
#60
0!
0#
1"
#70
1!
1#
