Day 8/Question 6/bcdtoxs3.v
module bcdtoxs3 (
    input  [3:0] bcd,
    output [3:0] xs3
);
assign xs3 = bcd + 4'b0011;
endmodule


/*output
meenakshi@meenakshi-Inspiron-3501:~/verilog/bcdtoxs3$ vvp bcdtoxs3.out
VCD info: dumpfile bcdtoxs3.vcd opened for output.
t=0 | BCD=0000 (0) | XS3=0011
t=10 | BCD=0001 (1) | XS3=0100
t=20 | BCD=0010 (2) | XS3=0101
t=30 | BCD=0011 (3) | XS3=0110
t=40 | BCD=0100 (4) | XS3=0111
t=50 | BCD=0101 (5) | XS3=1000
t=60 | BCD=0110 (6) | XS3=1001
t=70 | BCD=0111 (7) | XS3=1010
t=80 | BCD=1000 (8) | XS3=1011
t=90 | BCD=1001 (9) | XS3=1100
t=100 | BCD=1010 (10) | XS3=1101
bcdtoxs3_tb.v:23: $finish called at 110 (1s)
*/

Day 8/Question 6/bcdtoxs3_tb.v
module bcdtoxs3_tb;
    reg  [3:0] bcd;
    wire [3:0] xs3;
    bcdtoxs3 dut (
        .bcd(bcd),
        .xs3(xs3)
    );
    initial begin
        $dumpfile("bcdtoxs3.vcd");
        $dumpvars(0, bcdtoxs3_tb);
        $monitor("t=%0t | BCD=%b (%0d) | XS3=%b", $time, bcd, bcd, xs3);
        bcd = 4'd0; #10;
        bcd = 4'd1; #10;
        bcd = 4'd2; #10;
        bcd = 4'd3; #10;
        bcd = 4'd4; #10;
        bcd = 4'd5; #10;
        bcd = 4'd6; #10;
        bcd = 4'd7; #10;
        bcd = 4'd8; #10;
        bcd = 4'd9; #10;
        bcd = 4'd10; #10;
        $finish;
    end
endmodule

Day 8/Question 6/bcdtoxs3.vcd
$date
	Mon Dec 22 20:51:48 2025
$end
$version
	Icarus Verilog
$end
$timescale
	1s
$end
$scope module bcdtoxs3_tb $end
$var wire 4 ! xs3 [3:0] $end
$var reg 4 " bcd [3:0] $end
$scope module dut $end
$var wire 4 # bcd [3:0] $end
$var wire 4 $ xs3 [3:0] $end
$upscope $end
$upscope $end
$enddefinitions $end
$comment Show the parameter values. $end
$dumpall
$end
#0
$dumpvars
b11 $
b0 #
b0 "
b11 !
$end
#10
b100 !
b100 $
b1 "
b1 #
#20
b101 !
b101 $
b10 "
b10 #
#30
b110 !
b110 $
b11 "
b11 #
#40
b111 !
b111 $
b100 "
b100 #
#50
b1000 !
b1000 $
b101 "
b101 #
#60
b1001 !
b1001 $
b110 "
b110 #
#70
b1010 !
b1010 $
b111 "
b111 #
#80
b1011 !
b1011 $
b1000 "
b1000 #
#90
b1100 !
b1100 $
b1001 "
b1001 #
#100
b1101 !
b1101 $
b1010 "
b1010 #
