FSM/mealy machine/Question 3/mooreoverlappingsequence101.v
module mooreoverlappingsequence101 (
    input clk,
    input rst,
    input x,
    output reg y
);
 reg [1:0] state, next_state;
 always @(posedge clk or posedge rst) begin
   if (rst)
     state <= 2'b00;
   else
            state <= next_state;
   end
 always @(*) begin
   if (state == 2'b00) begin
   if (x)
      next_state = 2'b01;
   else
      next_state = 2'b00;
   end
   else if (state == 2'b01) begin
   if (x)
      next_state = 2'b01;
   else
      next_state = 2'b10;
   end
   else if (state == 2'b10) begin
   if (x)
      next_state = 2'b11;
   else
      next_state = 2'b00;
   end
   else if (state == 2'b11) begin
   if (x)
      next_state = 2'b01;
   else
      next_state = 2'b10;
   end
   else begin
      next_state = 2'b00;
        end
    end

    always @(*) begin
        if (state == 2'b11)
            y = 1'b1;
        else
            y = 1'b0;
    end
endmodule

/*output
meenakshi@meenakshi-Inspiron-3501:~/verilog/mooreoverlappingsequence101$ vvp mooreoverlappingsequence101.out
VCD info: dumpfile mooreoverlappingsequence101.vcd opened for output.
$time=0|clk=0|rst=1|x=0|y=0
$time=5|clk=1|rst=1|x=0|y=0
$time=10|clk=0|rst=0|x=0|y=0
$time=15|clk=1|rst=0|x=0|y=0
$time=20|clk=0|rst=0|x=1|y=0
$time=25|clk=1|rst=0|x=1|y=0
$time=30|clk=0|rst=0|x=0|y=0
$time=35|clk=1|rst=0|x=0|y=0
$time=40|clk=0|rst=0|x=1|y=0
$time=45|clk=1|rst=0|x=1|y=1
$time=50|clk=0|rst=0|x=0|y=1
$time=55|clk=1|rst=0|x=0|y=0
$time=60|clk=0|rst=0|x=1|y=0
$time=65|clk=1|rst=0|x=1|y=1
$time=70|clk=0|rst=0|x=1|y=1
$time=75|clk=1|rst=0|x=1|y=0
$time=80|clk=0|rst=0|x=0|y=0
$time=85|clk=1|rst=0|x=0|y=0
$time=90|clk=0|rst=0|x=0|y=0
$time=95|clk=1|rst=0|x=0|y=0
mooreoverlappingsequence101_tb.v:21: $finish called at 100 (1s)
$time=100|clk=0|rst=0|x=0|y=0
*/

FSM/moore machine/Question 1/mooreoverlappingsequence101_tb.v
module mooreoverlappingsequence101_tb;
 reg clk, rst, x;
 wire y;
 mooreoverlappingsequence101 dut(clk, rst, x, y);
 always #5 clk = ~clk;
 initial begin
 $monitor("$time=%0t|clk=%b|rst=%b|x=%b|y=%b",$time,clk,rst,x,y);
 $dumpfile("mooreoverlappingsequence101.vcd");
 $dumpvars(0,mooreoverlappingsequence101_tb); 
     clk = 0;
     rst = 1;
     x = 0;
     #10 rst = 0;
     #10 x = 1;
     #10 x = 0;
     #10 x = 1;
     #10 x = 0;
     #10 x = 1;
     #10 x = 1;
     #10 x = 0;
     #20 $finish;
end
endmodule

FSM/mealy machine/Question 3/mooreoverlappingsequence101.vcd
$date
	Tue Dec 30 16:59:01 2025
$end
$version
	Icarus Verilog
$end
$timescale
	1s
$end
$scope module mooreoverlappingsequence101_tb $end
$var wire 1 ! y $end
$var reg 1 " clk $end
$var reg 1 # rst $end
$var reg 1 $ x $end
$scope module dut $end
$var wire 1 " clk $end
$var wire 1 # rst $end
$var wire 1 $ x $end
$var reg 2 % next_state [1:0] $end
$var reg 2 & state [1:0] $end
$var reg 1 ! y $end
$upscope $end
$upscope $end
$enddefinitions $end
$comment Show the parameter values. $end
$dumpall
$end
#0
$dumpvars
b0 &
b0 %
0$
1#
0"
0!
$end
#5
1"
#10
0"
0#
#15
1"
#20
b1 %
0"
1$
#25
b1 &
1"
#30
b10 %
0"
0$
#35
b0 %
b10 &
1"
#40
b11 %
0"
1$
#45
1!
b1 %
b11 &
1"
#50
b10 %
0"
0$
#55
0!
b0 %
b10 &
1"
#60
b11 %
0"
1$
#65
1!
b1 %
b11 &
1"
#70
0"
#75
0!
b1 &
1"
#80
b10 %
0"
0$
#85
b0 %
b10 &
1"
#90
0"
#95
b0 &
1"
