Day 1/Question 8/mux2to1.v
module mux2to1(
    input a, b, s,
    output y  
);
    wire s_bar, x, z;

    not (s_bar, s);     
    and (x, s_bar, a);  
    and (z, s, b);     
    or  (y, x, z);      
endmodule





/* OUTPUT 
meenakshi@meenakshi-Inspiron-3501:~/verilog/mux2to1$ vvp mux2to1.vvp
VCD info: dumpfile mux2to1.vcd opened for output.
$time=0 | a=0 b=0 s=0 y=0
$time=10 | a=0 b=1 s=0 y=0
$time=20 | a=1 b=0 s=0 y=1
$time=30 | a=1 b=1 s=0 y=1
$time=40 | a=0 b=0 s=1 y=0
$time=50 | a=0 b=1 s=1 y=1
$time=60 | a=1 b=0 s=1 y=0
$time=70 | a=1 b=1 s=1 y=1
mux2to1_tb.v:30: $finish called at 80 (1s)
*/

Day 1/Question 8/mux2to1_tb.v
module mux2to1_tb;

    reg a, b, s;
    wire y;

    mux2to1 dut (
        .a(a),
        .b(b),
        .s(s),
        .y(y)
    );

    initial begin
        $dumpfile("mux2to1.vcd");
        $dumpvars(0, mux2to1_tb);

        $monitor("$time=%0t | a=%b b=%b s=%b y=%b",
                 $time, a, b, s, y);

        a=0; b=0; s=0; #10
        a=0; b=1; s=0; #10
        a=1; b=0; s=0; #10
        a=1; b=1; s=0; #10

        a=0; b=0; s=1; #10
        a=0; b=1; s=1; #10
        a=1; b=0; s=1; #10
        a=1; b=1; s=1; #10

        $finish;
    end
endmodule

Day 1/Question 8/mux2to1.vcd
$date
	Sat Dec  6 10:17:29 2025
$end
$version
	Icarus Verilog
$end
$timescale
	1s
$end
$scope module mux2to1_tb $end
$var wire 1 ! y $end
$var reg 1 " a $end
$var reg 1 # b $end
$var reg 1 $ s $end
$scope module dut $end
$var wire 1 " a $end
$var wire 1 # b $end
$var wire 1 $ s $end
$var wire 1 % s_bar $end
$var wire 1 & x $end
$var wire 1 ! y $end
$var wire 1 ' z $end
$upscope $end
$upscope $end
$enddefinitions $end
$comment Show the parameter values. $end
$dumpall
$end
#0
$dumpvars
0'
0&
1%
0$
0#
0"
0!
$end
#10
1#
#20
1!
1&
0#
1"
#30
1#
#40
0!
0%
0&
1$
0#
0"
#50
1!
1'
1#
#60
0!
0'
0#
1"
#70
1!
1'
1#
