Day_10/Question 2/pipo.v
module pipo (
input clk,
input rst,
input [3:0] parallel_in,
output reg [3:0] parallel_out
);
always @(posedge clk or posedge rst) begin
 if (rst)
   parallel_out <= 4'b0000;
 else
   parallel_out <= parallel_in;
end
endmodule



/*output
meenakshi@meenakshi-Inspiron-3501:~/verilog/pipo$ vvp pipo.out
VCD info: dumpfile pipo.vcd opened for output.
$time=0| clk=0| rst=1| parallel_in| parallel_out 0 0
$time=5| clk=1| rst=1| parallel_in| parallel_out 0 0
$time=10| clk=0| rst=0| parallel_in| parallel_out 0 0
$time=15| clk=1| rst=0| parallel_in| parallel_out 0 0
$time=20| clk=0| rst=0| parallel_in| parallel_out10 0
$time=25| clk=1| rst=0| parallel_in| parallel_out1010
$time=30| clk=0| rst=0| parallel_in| parallel_out1510
$time=35| clk=1| rst=0| parallel_in| parallel_out1515
$time=40| clk=0| rst=0| parallel_in| parallel_out 515
$time=45| clk=1| rst=0| parallel_in| parallel_out 5 5
$time=50| clk=0| rst=0| parallel_in| parallel_out 5 5
$time=55| clk=1| rst=0| parallel_in| parallel_out 5 5
pipo_tb.v:24: $finish called at 60 (1s)
$time=60| clk=0| rst=0| parallel_in| parallel_out 5 5
*/

Day_10/Question 2/pipo_tb.v
module pipo_tb;
reg clk;
reg rst;
reg [3:0] parallel_in;
wire [3:0] parallel_out;
pipo dut (
   .clk(clk),
   .rst(rst),
   .parallel_in(parallel_in),
   .parallel_out(parallel_out)
);
always #5 clk = ~clk;
initial begin
$monitor("$time=%0t| clk=%b| rst=%b| parallel_in| parallel_out",$time,clk,rst,parallel_in,parallel_out);
$dumpfile("pipo.vcd");
$dumpvars(0,pipo_tb);
 clk = 0;
 rst = 1;
 parallel_in = 4'b0000;
 #10 rst = 0;
 #10 parallel_in = 4'b1010;
 #10 parallel_in = 4'b1111;
 #10 parallel_in = 4'b0101;
 #20 $finish;
end
endmodule

Day_10/Question 2/pipo.vcd
$date
	Sat Dec 27 14:00:01 2025
$end
$version
	Icarus Verilog
$end
$timescale
	1s
$end
$scope module pipo_tb $end
$var wire 4 ! parallel_out [3:0] $end
$var reg 1 " clk $end
$var reg 4 # parallel_in [3:0] $end
$var reg 1 $ rst $end
$scope module dut $end
$var wire 1 " clk $end
$var wire 4 % parallel_in [3:0] $end
$var wire 1 $ rst $end
$var reg 4 & parallel_out [3:0] $end
$upscope $end
$upscope $end
$enddefinitions $end
$comment Show the parameter values. $end
$dumpall
$end
#0
$dumpvars
b0 &
b0 %
1$
b0 #
0"
b0 !
$end
#5
1"
#10
0"
0$
#15
1"
#20
0"
b1010 #
b1010 %
#25
b1010 !
b1010 &
1"
#30
0"
b1111 #
b1111 %
#35
b1111 !
b1111 &
1"
#40
0"
b101 #
b101 %
#45
b101 !
b101 &
1"
