Day 7/Question 2/sevensegmentdecoder.v
module sevensegmentdecoder (
    input [3:0] bcd,
    output reg [6:0] seg
);
    always @(*) begin
        case (bcd)
            4'd0: seg = 7'b1111110;
            4'd1: seg = 7'b0110000;
            4'd2: seg = 7'b1101101;
            4'd3: seg = 7'b1111001;
            4'd4: seg = 7'b0110011;
            4'd5: seg = 7'b1011011;
            4'd6: seg = 7'b1011111;
            4'd7: seg = 7'b1110000;
            4'd8: seg = 7'b1111111;
            4'd9: seg = 7'b1111011;
            default: seg = 7'b0000000;
        endcase
    end
endmodule


/*output
meenakshi@meenakshi-Inspiron-3501:~/verilog/sevensegmentdecoder$ vvp sevensegmentdecoder.out
VCD info: dumpfile sevensegmentdecoder.vcd opened for output.
$time=0|bcd=0000|seg=1111110
$time=10|bcd=0001|seg=0110000
$time=20|bcd=0010|seg=1101101
$time=30|bcd=0011|seg=1111001
$time=40|bcd=0100|seg=0110011
$time=50|bcd=0101|seg=1011011
$time=60|bcd=0110|seg=1011111
$time=70|bcd=0111|seg=1110000
$time=80|bcd=1000|seg=1111111
$time=90|bcd=1001|seg=1111011
sevensegmentdecoder_tb.v:22: $finish called at 100 (1s)
*/

Day 7/Question 2/sevensegmentdecoder_tb.v
module sevensegmentdecoder_tb;
    reg  [3:0] bcd;
    wire [6:0] seg;
    sevensegmentdecoder dut (
        .bcd(bcd),
        .seg(seg)
    );
    initial begin
        $monitor("$time=%0t|bcd=%b|seg=%b",$time,bcd,seg);
        $dumpfile("sevensegmentdecoder.vcd");
        $dumpvars(0,sevensegmentdecoder_tb);
        bcd = 4'd0; #10;
        bcd = 4'd1; #10;
        bcd = 4'd2; #10;
        bcd = 4'd3; #10;
        bcd = 4'd4; #10;
        bcd = 4'd5; #10;
        bcd = 4'd6; #10;
        bcd = 4'd7; #10;
        bcd = 4'd8; #10;
        bcd = 4'd9; #10;
        $finish;
    end
endmodule

Day 7/Question 2/sevensegmentdecoder.vcd
$date
	Fri Dec 19 16:40:28 2025
$end
$version
	Icarus Verilog
$end
$timescale
	1s
$end
$scope module sevensegmentdecoder_tb $end
$var wire 7 ! seg [6:0] $end
$var reg 4 " bcd [3:0] $end
$scope module dut $end
$var wire 4 # bcd [3:0] $end
$var reg 7 $ seg [6:0] $end
$upscope $end
$upscope $end
$enddefinitions $end
$comment Show the parameter values. $end
$dumpall
$end
#0
$dumpvars
b1111110 $
b0 #
b0 "
b1111110 !
$end
#10
b110000 !
b110000 $
b1 "
b1 #
#20
b1101101 !
b1101101 $
b10 "
b10 #
#30
b1111001 !
b1111001 $
b11 "
b11 #
#40
b110011 !
b110011 $
b100 "
b100 #
#50
b1011011 !
b1011011 $
b101 "
b101 #
#60
b1011111 !
b1011111 $
b110 "
b110 #
#70
b1110000 !
b1110000 $
b111 "
b111 #
#80
b1111111 !
b1111111 $
b1000 "
b1000 #
#90
b1111011 !
b1111011 $
b1001 "
b1001 #
